parallel_corpus_mnbvc.py
alignment/__init__.py
alignment/batch_detector.py
alignment/batch_sequential_detector.py
alignment/batch_sequential_for_one_file.py
alignment/evaluate_segmentation.py
alignment/rule_based_detector.py
alignment/text_segmenter.py
alignment/utils.py
alignment/script/__init__.py
alignment/script/gpt_helper.py
alignment/script/preprocess.py
download_data/__init__.py
download_data/download_un_corpus.py
download_data/about_sitemap/__init__.py
download_data/about_sitemap/download_after_2000_year_pdf_to_loacl.py
download_data/about_sitemap/download_all_pdf_url.py
download_data/about_sitemap/get_pdf_link_information.py
parallel_corpus_mnbvc-1.0.8.dist-info/LICENSE
parallel_corpus_mnbvc-1.0.8.dist-info/METADATA
parallel_corpus_mnbvc-1.0.8.dist-info/WHEEL
parallel_corpus_mnbvc-1.0.8.dist-info/top_level.txt
parallel_corpus_mnbvc-1.0.8.dist-info/RECORD
